README.rst
setup.cfg
setup.py
tvdb_client/__init__.py
tvdb_client.egg-info/PKG-INFO
tvdb_client.egg-info/SOURCES.txt
tvdb_client.egg-info/dependency_links.txt
tvdb_client.egg-info/not-zip-safe
tvdb_client.egg-info/requires.txt
tvdb_client.egg-info/top_level.txt
tvdb_client/clients/ApiV1Client.py
tvdb_client/clients/ApiV2Client.py
tvdb_client/clients/__init__.py
tvdb_client/clients/shared.py
tvdb_client/exceptions/__init__.py
tvdb_client/exceptions/tvdb_exceptions.py
tvdb_client/tests/__init__.py
tvdb_client/tests/client.py
tvdb_client/utils/__init__.py
tvdb_client/utils/requests_util.py
tvdb_client/utils/utils.py